Metadata-Version: 2.1
Name: restpass
Version: 1.2
Summary: Terminal based graphical utility for generating restorable passwords
Home-page: https://github.com/BananaLoaf/restpass
Author: BananaLoaf
Author-email: bananaloaf@protonmail.com
Maintainer: BananaLoaf
Maintainer-email: bananaloaf@protonmail.com
License: MIT
Keywords: generator,password,passphrase,hash,restore
Platform: UNKNOWN
Classifier: Development Status :: 5 - Production/Stable
Classifier: Environment :: Console
Classifier: Environment :: Console :: Curses
Classifier: License :: OSI Approved :: MIT License
Classifier: Natural Language :: English
Classifier: Operating System :: MacOS
Classifier: Operating System :: POSIX
Classifier: Operating System :: Unix
Classifier: Programming Language :: Python :: 3.6
Classifier: Programming Language :: Python :: 3.7
Classifier: Topic :: Security
Classifier: Topic :: Utilities
